VsCodeChajianKaifaWendangFix1/README.md
VsCodeChajianKaifaWendangFix1/__init__.py
VsCodeChajianKaifaWendangFix1/__main__.py
VsCodeChajianKaifaWendangFix1/file.epub
VsCodeChajianKaifaWendangFix1/index.html
VsCodeChajianKaifaWendangFix1/css/__init__.py
VsCodeChajianKaifaWendangFix1/css/annotations.css
VsCodeChajianKaifaWendangFix1/css/main.css
VsCodeChajianKaifaWendangFix1/css/normalize.css
VsCodeChajianKaifaWendangFix1/css/popup.css
VsCodeChajianKaifaWendangFix1/font/__init__.py
VsCodeChajianKaifaWendangFix1/font/fontello.eot
VsCodeChajianKaifaWendangFix1/font/fontello.svg
VsCodeChajianKaifaWendangFix1/font/fontello.ttf
VsCodeChajianKaifaWendangFix1/font/fontello.woff
VsCodeChajianKaifaWendangFix1/img/__init__.py
VsCodeChajianKaifaWendangFix1/img/annotator-glyph-sprite.png
VsCodeChajianKaifaWendangFix1/img/annotator-icon-sprite.png
VsCodeChajianKaifaWendangFix1/img/apple-touch-icon.png
VsCodeChajianKaifaWendangFix1/img/cancelfullscreen.png
VsCodeChajianKaifaWendangFix1/img/close.png
VsCodeChajianKaifaWendangFix1/img/fullscreen.png
VsCodeChajianKaifaWendangFix1/img/loader.gif
VsCodeChajianKaifaWendangFix1/img/menu-icon.png
VsCodeChajianKaifaWendangFix1/img/save.png
VsCodeChajianKaifaWendangFix1/img/saved.png
VsCodeChajianKaifaWendangFix1/img/settings-s.png
VsCodeChajianKaifaWendangFix1/img/settings.png
VsCodeChajianKaifaWendangFix1/img/star.png
VsCodeChajianKaifaWendangFix1/js/__init__.py
VsCodeChajianKaifaWendangFix1/js/epub.js
VsCodeChajianKaifaWendangFix1/js/epub.min.js
VsCodeChajianKaifaWendangFix1/js/epub.min.map
VsCodeChajianKaifaWendangFix1/js/hooks.min.js
VsCodeChajianKaifaWendangFix1/js/hooks.min.map
VsCodeChajianKaifaWendangFix1/js/reader.js
VsCodeChajianKaifaWendangFix1/js/reader.js.map
VsCodeChajianKaifaWendangFix1/js/reader.min.js
VsCodeChajianKaifaWendangFix1/js/reader.min.map
VsCodeChajianKaifaWendangFix1/js/hooks/__init__.py
VsCodeChajianKaifaWendangFix1/js/hooks/extensions/__init__.py
VsCodeChajianKaifaWendangFix1/js/hooks/extensions/highlight.js
vs_code_chajian_kaifa_wendang_fix1-2025.3.25.0.dist-info/METADATA
vs_code_chajian_kaifa_wendang_fix1-2025.3.25.0.dist-info/WHEEL
vs_code_chajian_kaifa_wendang_fix1-2025.3.25.0.dist-info/entry_points.txt
vs_code_chajian_kaifa_wendang_fix1-2025.3.25.0.dist-info/top_level.txt
vs_code_chajian_kaifa_wendang_fix1-2025.3.25.0.dist-info/RECORD
